lab/__init__.py
lab/p1.py
lab/p2.py
lab/p3.py
lab/p4.py
lab/p5.py
lab/p6.py
lab/p7.py
lab/p8.py
skdir-0.1.5.dist-info/LICENSE
skdir-0.1.5.dist-info/METADATA
skdir-0.1.5.dist-info/WHEEL
skdir-0.1.5.dist-info/top_level.txt
skdir-0.1.5.dist-info/RECORD
