Metadata-Version: 2.1
Name: skdir
Version: 0.1.5
Summary: skdir
Home-page: UNKNOWN
Author: Sk
Author-email: karnamsharath3@gmail.com
License: UNKNOWN
Keywords: arithmetic,math,mathematics,python tutorial,avi upadhyay
Platform: UNKNOWN
Classifier: Development Status :: 1 - Planning
Classifier: Intended Audience :: Developers
Classifier: Programming Language :: Python :: 3
Classifier: Operating System :: Unix
Classifier: Operating System :: MacOS :: MacOS X
Classifier: Operating System :: Microsoft :: Windows
License-File: LICENSE
Requires-Dist: numpy (>=1.21.0)
Requires-Dist: scikit-learn (>=0.24.0)
Requires-Dist: matplotlib (>=3.4.0)
